{
  "name": "pack",
  "children": [
    {
      "name": "data",
      "children": [
        {
          "name": "pack1",
          "children": [
            { "name": "pack8", "value": 500 },
            { "name": "pack9", "value": 2000 },
            { "name": "pack10", "value": 6000 },
            { "name": "pack11", "value": 1000 },
            { "name": "pack12", "value": 1000 }
          ]
        },
        { "name": "pack2", "value": 500 },
        { "name": "pack3", "value": 2000 },
        { "name": "pack4", "value": 500 },
        { "name": "pack5", "value": 2000 },
        { "name": "pack6", "value": 1000 },
        { "name": "pack7", "value": 3000 }
      ]
    }
  ]
}
